{"info":{"year":"2024","version":"2","description":"Exported from roboflow.com","contributor":"","url":"https://public.roboflow.com/object-detection/undefined","date_created":"2024-11-14T16:24:06+00:00"},"licenses":[{"id":1,"url":"https://creativecommons.org/licenses/by/4.0/","name":"CC BY 4.0"}],"categories":[{"id":0,"name":"food","supercategory":"none"},{"id":1,"name":"food","supercategory":"food"},{"id":2,"name":"plate","supercategory":"food"}],"images":[{"id":0,"license":1,"file_name":"normal_bread_png.rf.f84d42f4e1373c55f0eac30b604c6768.jpg","height":480,"width":640,"date_captured":"2024-11-14T16:24:06+00:00"}],"annotations":[{"id":0,"image_id":0,"category_id":2,"bbox":[117,98,383,381],"area":145923,"segmentation":[[118,264,117,300,124,344,136,375,155,406,202,451,264,479,356,479,389,468,416,453,452,422,472,395,490,358,500,314,500,274,493,238,462,176,431,143,404,124,374,110,337,100,295,98,261,103,225,116,187,140,165,161,142,193,128,223]],"iscrowd":0},{"id":1,"image_id":0,"category_id":1,"bbox":[219,208,159,164],"area":26076,"segmentation":[[220,213.286,219,357.286,229,362.286,369,372.286,376,357.286,378,217.286,371,213.286,234,208.286]],"iscrowd":0}]}